{"trialId":"v25-DT-off-002","version":"v25","map":"DT-off","levelId":"custom-5f697a3b-742","aimbotOff":true,"trialNum":2,"trialDurationMs":90500,"finalKills":8,"finalDeaths":9,"shotsFired":17,"frameData":[{"t":0,"playerX":735,"playerZ":735,"hp":1,"dodgeActive":false,"dodgeMoveX":0,"dodgeMoveZ":0,"dodgeUrgency":0,"pathGuardEngaged":false,"pathGuardCrossCount":0,"predictedShellCount":0,"realShellCount":0,"aimHitProb":2.356194490192344,"aimBounces":0,"aimTargetId":null,"shellsInFlight":0,"shotsFiredCumulative":0},{"t":1100,"playerX":735,"playerZ":735,"hp":1,"dodgeActive":false,"dodgeMoveX":0,"dodgeMoveZ":0,"dodgeUrgency":0,"pathGuardEngaged":false,"pathGuardCrossCount":0,"predictedShellCount":0,"realShellCount":0,"aimHitProb":2.356194490192344,"aimBounces":0,"aimTargetId":null,"shellsInFlight":0,"shotsFiredCumulative":0},{"t":2200,"playerX":735,"playerZ":735,"hp":1,"dodgeActive":false,"dodgeMoveX":0,"dodgeMoveZ":0,"dodgeUrgency":0,"pathGuardEngaged":false,"pathGuardCrossCount":0,"predictedShellCount":0,"realShellCount":0,"aimHitProb":2.356194490192344,"aimBounces":0,"aimTargetId":null,"shellsInFlight":0,"shotsFiredCumulative":0},{"t":5600,"playerX":735,"playerZ":735,"hp":1,"dodgeActive":false,"dodgeMoveX":0,"dodgeMoveZ":0,"dodgeUrgency":0,"pathGuardEngaged":true,"pathGuardCrossCount":0,"predictedShellCount":0,"realShellCount":0,"aimHitProb":2.356194490192344,"aimBounces":0,"aimTargetId":null,"shellsInFlight":1,"shotsFiredCumulative":1},{"t":6700,"playerX":735,"playerZ":735,"hp":1,"dodgeActive":false,"dodgeMoveX":0,"dodgeMoveZ":0,"dodgeUrgency":0,"pathGuardEngaged":true,"pathGuardCrossCount":0,"predictedShellCount":0,"realShellCount":0,"aimHitProb":2.356194490192344,"aimBounces":0,"aimTargetId":null,"shellsInFlight":2,"shotsFiredCumulative":2},{"t":7800,"playerX":735,"playerZ":735,"hp":1,"dodgeActive":false,"dodgeMoveX":0,"dodgeMoveZ":0,"dodgeUrgency":0,"pathGuardEngaged":true,"pathGuardCrossCount":0,"predictedShellCount":0,"realShellCount":0,"aimHitProb":2.356194490192344,"aimBounces":0,"aimTargetId":null,"shellsInFlight":1,"shotsFiredCumulative":2},{"t":8900,"playerX":694,"playerZ":782,"hp":1,"dodgeActive":true,"dodgeMoveX":0.93,"dodgeMoveZ":0.38,"dodgeUrgency":0.45072687150279067,"pathGuardEngaged":true,"pathGuardCrossCount":0,"predictedShellCount":71,"realShellCount":10,"aimHitProb":2.4254929926514954,"aimBounces":0,"aimTargetId":null,"shellsInFlight":1,"shotsFiredCumulative":2},{"t":12300,"playerX":735,"playerZ":735,"hp":1,"dodgeActive":true,"dodgeMoveX":0.93,"dodgeMoveZ":0.38,"dodgeUrgency":0.45072687150279067,"pathGuardEngaged":true,"pathGuardCrossCount":0,"predictedShellCount":71,"realShellCount":10,"aimHitProb":2.356194490192344,"aimBounces":0,"aimTargetId":null,"shellsInFlight":1,"shotsFiredCumulative":3},{"t":13400,"playerX":735,"playerZ":735,"hp":1,"dodgeActive":true,"dodgeMoveX":0.93,"dodgeMoveZ":0.38,"dodgeUrgency":0.45072687150279067,"pathGuardEngaged":true,"pathGuardCrossCount":0,"predictedShellCount":71,"realShellCount":10,"aimHitProb":2.356194490192344,"aimBounces":0,"aimTargetId":null,"shellsInFlight":2,"shotsFiredCumulative":4},{"t":14500,"playerX":735,"playerZ":735,"hp":1,"dodgeActive":true,"dodgeMoveX":0.93,"dodgeMoveZ":0.38,"dodgeUrgency":0.45072687150279067,"pathGuardEngaged":true,"pathGuardCrossCount":0,"predictedShellCount":71,"realShellCount":10,"aimHitProb":2.356194490192344,"aimBounces":0,"aimTargetId":null,"shellsInFlight":1,"shotsFiredCumulative":4},{"t":15600,"playerX":709,"playerZ":778,"hp":1,"dodgeActive":true,"dodgeMoveX":-0.95,"dodgeMoveZ":-0.31,"dodgeUrgency":0.23586277507714135,"pathGuardEngaged":true,"pathGuardCrossCount":0,"predictedShellCount":71,"realShellCount":12,"aimHitProb":2.4101305108497115,"aimBounces":0,"aimTargetId":null,"shellsInFlight":1,"shotsFiredCumulative":4},{"t":16700,"playerX":655,"playerZ":832,"hp":1,"dodgeActive":true,"dodgeMoveX":-0.95,"dodgeMoveZ":-0.31,"dodgeUrgency":0.23586277507714135,"pathGuardEngaged":true,"pathGuardCrossCount":0,"predictedShellCount":71,"realShellCount":12,"aimHitProb":2.4936764037129002,"aimBounces":0,"aimTargetId":null,"shellsInFlight":0,"shotsFiredCumulative":4},{"t":17702,"playerX":671,"playerZ":852,"hp":1,"dodgeActive":true,"dodgeMoveX":-0.48,"dodgeMoveZ":0.88,"dodgeUrgency":1,"pathGuardEngaged":true,"pathGuardCrossCount":0,"predictedShellCount":71,"realShellCount":14,"aimHitProb":2.4930678498786634,"aimBounces":0,"aimTargetId":null,"shellsInFlight":0,"shotsFiredCumulative":4},{"t":18800,"playerX":676,"playerZ":847,"hp":1,"dodgeActive":true,"dodgeMoveX":-0.51,"dodgeMoveZ":0.86,"dodgeUrgency":1,"pathGuardEngaged":true,"pathGuardCrossCount":0,"predictedShellCount":71,"realShellCount":14,"aimHitProb":2.4854328980156914,"aimBounces":0,"aimTargetId":null,"shellsInFlight":0,"shotsFiredCumulative":4},{"t":19900,"playerX":677,"playerZ":902,"hp":1,"dodgeActive":true,"dodgeMoveX":0.37,"dodgeMoveZ":-0.93,"dodgeUrgency":0.8377052232295611,"pathGuardEngaged":true,"pathGuardCrossCount":0,"predictedShellCount":33,"realShellCount":7,"aimHitProb":2.519224515068382,"aimBounces":0,"aimTargetId":null,"shellsInFlight":0,"shotsFiredCumulative":4},{"t":21000,"playerX":657,"playerZ":905,"hp":1,"dodgeActive":true,"dodgeMoveX":0.71,"dodgeMoveZ":-0.71,"dodgeUrgency":1,"pathGuardEngaged":true,"pathGuardCrossCount":0,"predictedShellCount":62,"realShellCount":11,"aimHitProb":2.5376166258693686,"aimBounces":0,"aimTargetId":null,"shellsInFlight":0,"shotsFiredCumulative":4},{"t":22100,"playerX":674,"playerZ":897,"hp":1,"dodgeActive":true,"dodgeMoveX":-0.78,"dodgeMoveZ":-0.62,"dodgeUrgency":1,"pathGuardEngaged":true,"pathGuardCrossCount":0,"predictedShellCount":44,"realShellCount":11,"aimHitProb":2.5189051399518085,"aimBounces":0,"aimTargetId":null,"shellsInFlight":0,"shotsFiredCumulative":4},{"t":23200,"playerX":688,"playerZ":897,"hp":1,"dodgeActive":true,"dodgeMoveX":-0.78,"dodgeMoveZ":-0.62,"dodgeUrgency":1,"pathGuardEngaged":false,"pathGuardCrossCount":0,"predictedShellCount":44,"realShellCount":11,"aimHitProb":2.5072987137325526,"aimBounces":0,"aimTargetId":null,"shellsInFlight":0,"shotsFiredCumulative":4},{"t":24300,"playerX":728,"playerZ":871,"hp":1,"dodgeActive":true,"dodgeMoveX":-0.78,"dodgeMoveZ":0.63,"dodgeUrgency":0.8303582337511393,"pathGuardEngaged":true,"pathGuardCrossCount":0,"predictedShellCount":56,"realShellCount":6,"aimHitProb":2.458923355122142,"aimBounces":0,"aimTargetId":null,"shellsInFlight":0,"shotsFiredCumulative":4},{"t":25400,"playerX":742,"playerZ":866,"hp":1,"dodgeActive":true,"dodgeMoveX":-0.12,"dodgeMoveZ":-0.99,"dodgeUrgency":1,"pathGuardEngaged":true,"pathGuardCrossCount":0,"predictedShellCount":47,"realShellCount":8,"aimHitProb":2.4449268815626937,"aimBounces":0,"aimTargetId":null,"shellsInFlight":0,"shotsFiredCumulative":4},{"t":26500,"playerX":673,"playerZ":864,"hp":1,"dodgeActive":true,"dodgeMoveX":0.49,"dodgeMoveZ":0.87,"dodgeUrgency":1,"pathGuardEngaged":true,"pathGuardCrossCount":0,"predictedShellCount":29,"realShellCount":8,"aimHitProb":2.4996894177232623,"aimBounces":0,"aimTargetId":null,"shellsInFlight":0,"shotsFiredCumulative":4},{"t":27600,"playerX":681,"playerZ":874,"hp":1,"dodgeActive":true,"dodgeMoveX":0.49,"dodgeMoveZ":0.87,"dodgeUrgency":1,"pathGuardEngaged":false,"pathGuardCrossCount":0,"predictedShellCount":29,"realShellCount":8,"aimHitProb":2.4987939666673658,"aimBounces":0,"aimTargetId":null,"shellsInFlight":0,"shotsFiredCumulative":4},{"t":28700,"playerX":681,"playerZ":874,"hp":1,"dodgeActive":true,"dodgeMoveX":0.49,"dodgeMoveZ":0.87,"dodgeUrgency":1,"pathGuardEngaged":false,"pathGuardCrossCount":0,"predictedShellCount":29,"realShellCount":8,"aimHitProb":2.4987944683214742,"aimBounces":0,"aimTargetId":null,"shellsInFlight":0,"shotsFiredCumulative":4},{"t":29800,"playerX":588,"playerZ":867,"hp":1,"dodgeActive":true,"dodgeMoveX":0.55,"dodgeMoveZ":0.84,"dodgeUrgency":1,"pathGuardEngaged":true,"pathGuardCrossCount":0,"predictedShellCount":34,"realShellCount":7,"aimHitProb":2.5321419177326483,"aimBounces":0,"aimTargetId":null,"shellsInFlight":0,"shotsFiredCumulative":4},{"t":32400,"playerX":735,"playerZ":735,"hp":1,"dodgeActive":true,"dodgeMoveX":0.26,"dodgeMoveZ":0.97,"dodgeUrgency":0.8556755198185936,"pathGuardEngaged":true,"pathGuardCrossCount":0,"predictedShellCount":25,"realShellCount":6,"aimHitProb":2.356194490192344,"aimBounces":0,"aimTargetId":null,"shellsInFlight":1,"shotsFiredCumulative":5},{"t":33500,"playerX":735,"playerZ":735,"hp":1,"dodgeActive":true,"dodgeMoveX":0.26,"dodgeMoveZ":0.97,"dodgeUrgency":0.8556755198185936,"pathGuardEngaged":true,"pathGuardCrossCount":0,"predictedShellCount":25,"realShellCount":6,"aimHitProb":2.356194490192344,"aimBounces":0,"aimTargetId":null,"shellsInFlight":2,"shotsFiredCumulative":6},{"t":34600,"playerX":735,"playerZ":735,"hp":1,"dodgeActive":true,"dodgeMoveX":0.26,"dodgeMoveZ":0.97,"dodgeUrgency":0.8556755198185936,"pathGuardEngaged":true,"pathGuardCrossCount":0,"predictedShellCount":25,"realShellCount":6,"aimHitProb":2.356194490192344,"aimBounces":0,"aimTargetId":null,"shellsInFlight":1,"shotsFiredCumulative":6},{"t":35700,"playerX":734,"playerZ":784,"hp":1,"dodgeActive":true,"dodgeMoveX":-0.02,"dodgeMoveZ":-1,"dodgeUrgency":0.3024242477013311,"pathGuardEngaged":true,"pathGuardCrossCount":0,"predictedShellCount":71,"realShellCount":11,"aimHitProb":2.3942358148716423,"aimBounces":0,"aimTargetId":null,"shellsInFlight":1,"shotsFiredCumulative":6},{"t":38453,"playerX":735,"playerZ":735,"hp":1,"dodgeActive":true,"dodgeMoveX":-0.02,"dodgeMoveZ":-1,"dodgeUrgency":0.3024242477013311,"pathGuardEngaged":true,"pathGuardCrossCount":0,"predictedShellCount":71,"realShellCount":11,"aimHitProb":2.356194490192344,"aimBounces":0,"aimTargetId":null,"shellsInFlight":1,"shotsFiredCumulative":6},{"t":39500,"playerX":735,"playerZ":733,"hp":1,"dodgeActive":true,"dodgeMoveX":0.22,"dodgeMoveZ":0.97,"dodgeUrgency":0.49926815899378174,"pathGuardEngaged":true,"pathGuardCrossCount":0,"predictedShellCount":5,"realShellCount":1,"aimHitProb":2.354803670487877,"aimBounces":0,"aimTargetId":null,"shellsInFlight":2,"shotsFiredCumulative":7},{"t":40600,"playerX":735,"playerZ":733,"hp":1,"dodgeActive":true,"dodgeMoveX":0.22,"dodgeMoveZ":0.97,"dodgeUrgency":0.49926815899378174,"pathGuardEngaged":true,"pathGuardCrossCount":0,"predictedShellCount":5,"realShellCount":1,"aimHitProb":2.3548036705049924,"aimBounces":0,"aimTargetId":null,"shellsInFlight":1,"shotsFiredCumulative":7},{"t":41700,"playerX":782,"playerZ":717,"hp":1,"dodgeActive":true,"dodgeMoveX":0.14,"dodgeMoveZ":0.99,"dodgeUrgency":0.4749139291777842,"pathGuardEngaged":false,"pathGuardCrossCount":0,"predictedShellCount":71,"realShellCount":13,"aimHitProb":2.3057148795019096,"aimBounces":0,"aimTargetId":null,"shellsInFlight":1,"shotsFiredCumulative":7},{"t":42800,"playerX":818,"playerZ":641,"hp":1,"dodgeActive":true,"dodgeMoveX":0.14,"dodgeMoveZ":0.99,"dodgeUrgency":0.4749139291777842,"pathGuardEngaged":true,"pathGuardCrossCount":0,"predictedShellCount":71,"realShellCount":13,"aimHitProb":2.2154126945341623,"aimBounces":0,"aimTargetId":null,"shellsInFlight":0,"shotsFiredCumulative":7},{"t":46000,"playerX":735,"playerZ":735,"hp":1,"dodgeActive":true,"dodgeMoveX":0.59,"dodgeMoveZ":-0.81,"dodgeUrgency":0.9597006926307105,"pathGuardEngaged":true,"pathGuardCrossCount":0,"predictedShellCount":71,"realShellCount":14,"aimHitProb":2.356194490192344,"aimBounces":0,"aimTargetId":null,"shellsInFlight":1,"shotsFiredCumulative":8},{"t":47100,"playerX":735,"playerZ":735,"hp":1,"dodgeActive":true,"dodgeMoveX":0.59,"dodgeMoveZ":-0.81,"dodgeUrgency":0.9597006926307105,"pathGuardEngaged":true,"pathGuardCrossCount":0,"predictedShellCount":71,"realShellCount":14,"aimHitProb":2.356194490192344,"aimBounces":0,"aimTargetId":null,"shellsInFlight":2,"shotsFiredCumulative":9},{"t":48200,"playerX":735,"playerZ":735,"hp":1,"dodgeActive":true,"dodgeMoveX":0.59,"dodgeMoveZ":-0.81,"dodgeUrgency":0.9597006926307105,"pathGuardEngaged":true,"pathGuardCrossCount":0,"predictedShellCount":71,"realShellCount":14,"aimHitProb":2.356194490192344,"aimBounces":0,"aimTargetId":null,"shellsInFlight":1,"shotsFiredCumulative":9},{"t":49300,"playerX":715,"playerZ":767,"hp":1,"dodgeActive":true,"dodgeMoveX":1,"dodgeMoveZ":0.05,"dodgeUrgency":0.3661696775998923,"pathGuardEngaged":false,"pathGuardCrossCount":0,"predictedShellCount":71,"realShellCount":12,"aimHitProb":2.3972684659383106,"aimBounces":0,"aimTargetId":null,"shellsInFlight":1,"shotsFiredCumulative":9},{"t":50400,"playerX":639,"playerZ":821,"hp":1,"dodgeActive":true,"dodgeMoveX":1,"dodgeMoveZ":0.05,"dodgeUrgency":0.3661696775998923,"pathGuardEngaged":true,"pathGuardCrossCount":0,"predictedShellCount":71,"realShellCount":12,"aimHitProb":2.500949078026027,"aimBounces":0,"aimTargetId":null,"shellsInFlight":1,"shotsFiredCumulative":9},{"t":51500,"playerX":641,"playerZ":791,"hp":1,"dodgeActive":true,"dodgeMoveX":0.98,"dodgeMoveZ":0.18,"dodgeUrgency":1,"pathGuardEngaged":true,"pathGuardCrossCount":0,"predictedShellCount":65,"realShellCount":19,"aimHitProb":2.4790984907897293,"aimBounces":0,"aimTargetId":null,"shellsInFlight":0,"shotsFiredCumulative":9},{"t":52600,"playerX":637,"playerZ":775,"hp":1,"dodgeActive":true,"dodgeMoveX":1,"dodgeMoveZ":0.1,"dodgeUrgency":1,"pathGuardEngaged":false,"pathGuardCrossCount":0,"predictedShellCount":71,"realShellCount":19,"aimHitProb":2.470230015146182,"aimBounces":0,"aimTargetId":null,"shellsInFlight":0,"shotsFiredCumulative":9},{"t":53700,"playerX":640,"playerZ":740,"hp":1,"dodgeActive":true,"dodgeMoveX":-0.03,"dodgeMoveZ":1,"dodgeUrgency":0.6927372583229888,"pathGuardEngaged":false,"pathGuardCrossCount":0,"predictedShellCount":63,"realShellCount":8,"aimHitProb":2.442043711858691,"aimBounces":0,"aimTargetId":null,"shellsInFlight":0,"shotsFiredCumulative":9},{"t":54701,"playerX":646,"playerZ":713,"hp":1,"dodgeActive":true,"dodgeMoveX":0.91,"dodgeMoveZ":0.42,"dodgeUrgency":0.8154548854954207,"pathGuardEngaged":false,"pathGuardCrossCount":0,"predictedShellCount":60,"realShellCount":5,"aimHitProb":2.4140623594681685,"aimBounces":0,"aimTargetId":null,"shellsInFlight":0,"shotsFiredCumulative":9},{"t":55800,"playerX":629,"playerZ":722,"hp":1,"dodgeActive":true,"dodgeMoveX":0.91,"dodgeMoveZ":0.41,"dodgeUrgency":1,"pathGuardEngaged":true,"pathGuardCrossCount":0,"predictedShellCount":60,"realShellCount":7,"aimHitProb":2.4374252615355374,"aimBounces":0,"aimTargetId":null,"shellsInFlight":0,"shotsFiredCumulative":9},{"t":56900,"playerX":599,"playerZ":775,"hp":1,"dodgeActive":true,"dodgeMoveX":-0.77,"dodgeMoveZ":-0.64,"dodgeUrgency":1,"pathGuardEngaged":true,"pathGuardCrossCount":0,"predictedShellCount":28,"realShellCount":6,"aimHitProb":2.506749696321922,"aimBounces":0,"aimTargetId":null,"shellsInFlight":0,"shotsFiredCumulative":9},{"t":58000,"playerX":595,"playerZ":778,"hp":1,"dodgeActive":true,"dodgeMoveX":-0.77,"dodgeMoveZ":-0.64,"dodgeUrgency":1,"pathGuardEngaged":true,"pathGuardCrossCount":0,"predictedShellCount":28,"realShellCount":6,"aimHitProb":2.511957870534932,"aimBounces":0,"aimTargetId":null,"shellsInFlight":0,"shotsFiredCumulative":9},{"t":59100,"playerX":658,"playerZ":791,"hp":1,"dodgeActive":true,"dodgeMoveX":-0.42,"dodgeMoveZ":0.91,"dodgeUrgency":0.6289906435752575,"pathGuardEngaged":true,"pathGuardCrossCount":0,"predictedShellCount":34,"realShellCount":4,"aimHitProb":2.46288399725322,"aimBounces":0,"aimTargetId":null,"shellsInFlight":0,"shotsFiredCumulative":9},{"t":60200,"playerX":660,"playerZ":789,"hp":1,"dodgeActive":true,"dodgeMoveX":0.56,"dodgeMoveZ":-0.83,"dodgeUrgency":1,"pathGuardEngaged":true,"pathGuardCrossCount":0,"predictedShellCount":56,"realShellCount":4,"aimHitProb":2.459577415105029,"aimBounces":0,"aimTargetId":null,"shellsInFlight":0,"shotsFiredCumulative":9},{"t":61300,"playerX":660,"playerZ":789,"hp":1,"dodgeActive":true,"dodgeMoveX":0.56,"dodgeMoveZ":-0.83,"dodgeUrgency":1,"pathGuardEngaged":true,"pathGuardCrossCount":0,"predictedShellCount":56,"realShellCount":4,"aimHitProb":2.4595376878310766,"aimBounces":0,"aimTargetId":null,"shellsInFlight":0,"shotsFiredCumulative":9},{"t":62400,"playerX":660,"playerZ":789,"hp":1,"dodgeActive":true,"dodgeMoveX":0.56,"dodgeMoveZ":-0.83,"dodgeUrgency":1,"pathGuardEngaged":true,"pathGuardCrossCount":0,"predictedShellCount":56,"realShellCount":4,"aimHitProb":2.4595376877939295,"aimBounces":0,"aimTargetId":null,"shellsInFlight":0,"shotsFiredCumulative":9},{"t":63500,"playerX":672,"playerZ":790,"hp":1,"dodgeActive":true,"dodgeMoveX":0.37,"dodgeMoveZ":0.93,"dodgeUrgency":0.481184718418854,"pathGuardEngaged":false,"pathGuardCrossCount":0,"predictedShellCount":53,"realShellCount":7,"aimHitProb":2.4502696743770684,"aimBounces":0,"aimTargetId":null,"shellsInFlight":0,"shotsFiredCumulative":9},{"t":64600,"playerX":752,"playerZ":836,"hp":1,"dodgeActive":true,"dodgeMoveX":0.37,"dodgeMoveZ":0.93,"dodgeUrgency":0.481184718418854,"pathGuardEngaged":true,"pathGuardCrossCount":0,"predictedShellCount":53,"realShellCount":7,"aimHitProb":2.4165619182898244,"aimBounces":0,"aimTargetId":null,"shellsInFlight":0,"shotsFiredCumulative":9},{"t":65700,"playerX":816,"playerZ":835,"hp":1,"dodgeActive":true,"dodgeMoveX":-0.7,"dodgeMoveZ":0.71,"dodgeUrgency":1,"pathGuardEngaged":true,"pathGuardCrossCount":0,"predictedShellCount":42,"realShellCount":11,"aimHitProb":2.3698885180966496,"aimBounces":0,"aimTargetId":null,"shellsInFlight":0,"shotsFiredCumulative":9},{"t":66800,"playerX":847,"playerZ":847,"hp":1,"dodgeActive":true,"dodgeMoveX":-1,"dodgeMoveZ":-0.06,"dodgeUrgency":1,"pathGuardEngaged":true,"pathGuardCrossCount":0,"predictedShellCount":53,"realShellCount":14,"aimHitProb":2.3561405137189873,"aimBounces":0,"aimTargetId":null,"shellsInFlight":0,"shotsFiredCumulative":9},{"t":69390,"playerX":735,"playerZ":735,"hp":1,"dodgeActive":true,"dodgeMoveX":-0.88,"dodgeMoveZ":-0.47,"dodgeUrgency":1,"pathGuardEngaged":true,"pathGuardCrossCount":0,"predictedShellCount":39,"realShellCount":14,"aimHitProb":2.356194490192344,"aimBounces":0,"aimTargetId":null,"shellsInFlight":1,"shotsFiredCumulative":10},{"t":70400,"playerX":735,"playerZ":733,"hp":1,"dodgeActive":true,"dodgeMoveX":0.32,"dodgeMoveZ":0.95,"dodgeUrgency":0.37774307335292767,"pathGuardEngaged":true,"pathGuardCrossCount":0,"predictedShellCount":7,"realShellCount":1,"aimHitProb":2.3548036704737694,"aimBounces":0,"aimTargetId":null,"shellsInFlight":2,"shotsFiredCumulative":11},{"t":71500,"playerX":735,"playerZ":733,"hp":1,"dodgeActive":true,"dodgeMoveX":0.32,"dodgeMoveZ":0.95,"dodgeUrgency":0.37774307335292767,"pathGuardEngaged":true,"pathGuardCrossCount":0,"predictedShellCount":7,"realShellCount":1,"aimHitProb":2.3548036705049924,"aimBounces":0,"aimTargetId":null,"shellsInFlight":1,"shotsFiredCumulative":11},{"t":72600,"playerX":733,"playerZ":731,"hp":1,"dodgeActive":true,"dodgeMoveX":0.32,"dodgeMoveZ":0.95,"dodgeUrgency":0.37774307335292767,"pathGuardEngaged":true,"pathGuardCrossCount":0,"predictedShellCount":7,"realShellCount":1,"aimHitProb":2.354588457150985,"aimBounces":0,"aimTargetId":null,"shellsInFlight":1,"shotsFiredCumulative":11},{"t":75780,"playerX":735,"playerZ":735,"hp":1,"dodgeActive":true,"dodgeMoveX":0.32,"dodgeMoveZ":0.95,"dodgeUrgency":0.37774307335292767,"pathGuardEngaged":true,"pathGuardCrossCount":0,"predictedShellCount":7,"realShellCount":1,"aimHitProb":2.356194490192344,"aimBounces":0,"aimTargetId":null,"shellsInFlight":0,"shotsFiredCumulative":11},{"t":76800,"playerX":735,"playerZ":735,"hp":1,"dodgeActive":true,"dodgeMoveX":0.32,"dodgeMoveZ":0.95,"dodgeUrgency":0.37774307335292767,"pathGuardEngaged":true,"pathGuardCrossCount":0,"predictedShellCount":7,"realShellCount":1,"aimHitProb":2.356194490192344,"aimBounces":0,"aimTargetId":null,"shellsInFlight":3,"shotsFiredCumulative":14},{"t":77900,"playerX":735,"playerZ":735,"hp":1,"dodgeActive":true,"dodgeMoveX":0.32,"dodgeMoveZ":0.95,"dodgeUrgency":0.37774307335292767,"pathGuardEngaged":true,"pathGuardCrossCount":0,"predictedShellCount":7,"realShellCount":1,"aimHitProb":2.356194490192344,"aimBounces":0,"aimTargetId":null,"shellsInFlight":0,"shotsFiredCumulative":14},{"t":79000,"playerX":750,"playerZ":710,"hp":1,"dodgeActive":true,"dodgeMoveX":0.06,"dodgeMoveZ":1,"dodgeUrgency":0.46912114791909426,"pathGuardEngaged":false,"pathGuardCrossCount":0,"predictedShellCount":71,"realShellCount":13,"aimHitProb":2.3235473950636205,"aimBounces":0,"aimTargetId":null,"shellsInFlight":0,"shotsFiredCumulative":14},{"t":80100,"playerX":804,"playerZ":660,"hp":1,"dodgeActive":true,"dodgeMoveX":0.06,"dodgeMoveZ":1,"dodgeUrgency":0.46912114791909426,"pathGuardEngaged":true,"pathGuardCrossCount":0,"predictedShellCount":71,"realShellCount":13,"aimHitProb":2.24153452244715,"aimBounces":0,"aimTargetId":null,"shellsInFlight":0,"shotsFiredCumulative":14},{"t":82855,"playerX":735,"playerZ":735,"hp":1,"dodgeActive":true,"dodgeMoveX":0.31,"dodgeMoveZ":-0.95,"dodgeUrgency":0.9995832449257536,"pathGuardEngaged":true,"pathGuardCrossCount":0,"predictedShellCount":71,"realShellCount":16,"aimHitProb":2.356194490192344,"aimBounces":0,"aimTargetId":null,"shellsInFlight":1,"shotsFiredCumulative":15},{"t":83900,"playerX":735,"playerZ":735,"hp":1,"dodgeActive":true,"dodgeMoveX":0.31,"dodgeMoveZ":-0.95,"dodgeUrgency":0.9995832449257536,"pathGuardEngaged":true,"pathGuardCrossCount":0,"predictedShellCount":71,"realShellCount":16,"aimHitProb":2.356194490192344,"aimBounces":0,"aimTargetId":null,"shellsInFlight":2,"shotsFiredCumulative":16},{"t":85000,"playerX":735,"playerZ":735,"hp":1,"dodgeActive":true,"dodgeMoveX":0.31,"dodgeMoveZ":-0.95,"dodgeUrgency":0.9995832449257536,"pathGuardEngaged":true,"pathGuardCrossCount":0,"predictedShellCount":71,"realShellCount":16,"aimHitProb":2.356194490192344,"aimBounces":0,"aimTargetId":null,"shellsInFlight":1,"shotsFiredCumulative":16},{"t":86100,"playerX":729,"playerZ":717,"hp":1,"dodgeActive":true,"dodgeMoveX":-0.21,"dodgeMoveZ":-0.98,"dodgeUrgency":0.4470567060305518,"pathGuardEngaged":false,"pathGuardCrossCount":0,"predictedShellCount":71,"realShellCount":10,"aimHitProb":2.3462542901393224,"aimBounces":0,"aimTargetId":null,"shellsInFlight":1,"shotsFiredCumulative":16},{"t":89400,"playerX":735,"playerZ":735,"hp":1,"dodgeActive":true,"dodgeMoveX":-0.21,"dodgeMoveZ":-0.98,"dodgeUrgency":0.4470567060305518,"pathGuardEngaged":true,"pathGuardCrossCount":0,"predictedShellCount":71,"realShellCount":10,"aimHitProb":2.356194490192344,"aimBounces":0,"aimTargetId":null,"shellsInFlight":1,"shotsFiredCumulative":16},{"t":90500,"playerX":735,"playerZ":735,"hp":1,"dodgeActive":true,"dodgeMoveX":-0.21,"dodgeMoveZ":-0.98,"dodgeUrgency":0.4470567060305518,"pathGuardEngaged":true,"pathGuardCrossCount":0,"predictedShellCount":71,"realShellCount":10,"aimHitProb":2.356194490192344,"aimBounces":0,"aimTargetId":null,"shellsInFlight":2,"shotsFiredCumulative":17}],"events":[{"type":"boot","t":0,"data":{"mode":"passive"}},{"type":"death","t":3392,"data":{"deathNum":1,"wave":0,"kills":0,"pos":[722,683],"cause":"enemy_shell","killer":{"ownerId":"28","isOwnShell":false,"dist":68,"shellSpeed":320,"shellPos":[695,746],"shellType":320,"shellAgeS":1.69,"playerMovingTowardShell":false,"dodgeTowardShell":false},"playerSpeed":0,"playerVel":[0,0],"dodgeActive":false,"dodgeUrgency":0,"dodgeMoveX":0,"dodgeMoveZ":0,"interceptActive":false,"timeSinceLastFire":-1,"enemies":72,"incomingShells":20,"spawnToDeathS":3.4,"dodgeDurationS":0,"shellAgeS":1.69,"playerMovingTowardShell":false,"dodgeTowardShell":false}},{"type":"spawn","t":5600,"data":{"pos":[735,735]}},{"type":"kill","t":7200,"data":{"killNum":1,"wave":0}},{"type":"death","t":10056,"data":{"deathNum":2,"wave":0,"kills":1,"pos":[640,808],"cause":"unknown","killer":null,"playerSpeed":0,"playerVel":[0,0],"dodgeActive":true,"dodgeUrgency":0.45072687150279067,"dodgeMoveX":0.93,"dodgeMoveZ":0.38,"interceptActive":false,"timeSinceLastFire":-1,"enemies":71,"incomingShells":27,"spawnToDeathS":4.5,"dodgeDurationS":1.7,"shellAgeS":-1,"playerMovingTowardShell":false,"dodgeTowardShell":false}},{"type":"spawn","t":12300,"data":{"pos":[735,735]}},{"type":"kill","t":13900,"data":{"killNum":2,"wave":0}},{"type":"death","t":30171,"data":{"deathNum":3,"wave":0,"kills":2,"pos":[582,867],"cause":"unknown","killer":null,"playerSpeed":0,"playerVel":[0,0],"dodgeActive":true,"dodgeUrgency":0.9824775164400699,"dodgeMoveX":-1,"dodgeMoveZ":-0.01,"interceptActive":false,"timeSinceLastFire":-1,"enemies":50,"incomingShells":6,"spawnToDeathS":17.9,"dodgeDurationS":21.8,"shellAgeS":-1,"playerMovingTowardShell":false,"dodgeTowardShell":false}},{"type":"spawn","t":32400,"data":{"pos":[735,735]}},{"type":"kill","t":34000,"data":{"killNum":3,"wave":0}},{"type":"death","t":36240,"data":{"deathNum":4,"wave":0,"kills":3,"pos":[731,807],"cause":"enemy_shell","killer":{"ownerId":"385","isOwnShell":false,"dist":79,"shellSpeed":320,"shellPos":[714,884],"shellType":320,"shellAgeS":1.34,"playerMovingTowardShell":false,"dodgeTowardShell":false},"playerSpeed":0,"playerVel":[0,0],"dodgeActive":true,"dodgeUrgency":0.3024242477013311,"dodgeMoveX":-0.02,"dodgeMoveZ":-1,"interceptActive":false,"timeSinceLastFire":-1,"enemies":71,"incomingShells":20,"spawnToDeathS":3.8,"dodgeDurationS":27.9,"shellAgeS":1.34,"playerMovingTowardShell":false,"dodgeTowardShell":false}},{"type":"spawn","t":38453,"data":{"pos":[735,735]}},{"type":"kill","t":40100,"data":{"killNum":4,"wave":0}},{"type":"death","t":43769,"data":{"deathNum":5,"wave":0,"kills":4,"pos":[804,637],"cause":"enemy_shell","killer":{"ownerId":"446","isOwnShell":false,"dist":41,"shellSpeed":320,"shellPos":[833,665],"shellType":320,"shellAgeS":2.07,"playerMovingTowardShell":false,"dodgeTowardShell":false},"playerSpeed":0,"playerVel":[0,0],"dodgeActive":true,"dodgeUrgency":1,"dodgeMoveX":-0.47,"dodgeMoveZ":-0.88,"interceptActive":false,"timeSinceLastFire":-1,"enemies":71,"incomingShells":14,"spawnToDeathS":5.3,"dodgeDurationS":35.4,"shellAgeS":2.07,"playerMovingTowardShell":false,"dodgeTowardShell":false}},{"type":"spawn","t":46000,"data":{"pos":[735,735]}},{"type":"kill","t":47600,"data":{"killNum":5,"wave":0}},{"type":"death","t":67182,"data":{"deathNum":6,"wave":0,"kills":5,"pos":[851,846],"cause":"unknown","killer":null,"playerSpeed":0,"playerVel":[0,0],"dodgeActive":true,"dodgeUrgency":1,"dodgeMoveX":-0.88,"dodgeMoveZ":-0.47,"interceptActive":false,"timeSinceLastFire":-1,"enemies":52,"incomingShells":13,"spawnToDeathS":21.2,"dodgeDurationS":58.9,"shellAgeS":-1,"playerMovingTowardShell":false,"dodgeTowardShell":false}},{"type":"spawn","t":69390,"data":{"pos":[735,735]}},{"type":"kill","t":71000,"data":{"killNum":6,"wave":0}},{"type":"death","t":73597,"data":{"deathNum":7,"wave":0,"kills":6,"pos":[732,659],"cause":"enemy_shell","killer":{"ownerId":"660","isOwnShell":false,"dist":26,"shellSpeed":320,"shellPos":[706,661],"shellType":320,"shellAgeS":1.7,"playerMovingTowardShell":false,"dodgeTowardShell":false},"playerSpeed":0,"playerVel":[0,0],"dodgeActive":true,"dodgeUrgency":0.37774307335292767,"dodgeMoveX":0.32,"dodgeMoveZ":0.95,"interceptActive":false,"timeSinceLastFire":-1,"enemies":71,"incomingShells":22,"spawnToDeathS":4.2,"dodgeDurationS":65.3,"shellAgeS":1.7,"playerMovingTowardShell":false,"dodgeTowardShell":false}},{"type":"spawn","t":75780,"data":{"pos":[735,735]}},{"type":"kill","t":77400,"data":{"killNum":7,"wave":0}},{"type":"death","t":80642,"data":{"deathNum":8,"wave":0,"kills":7,"pos":[817,667],"cause":"unknown","killer":null,"playerSpeed":0,"playerVel":[0,0],"dodgeActive":true,"dodgeUrgency":1,"dodgeMoveX":0.96,"dodgeMoveZ":0.29,"interceptActive":false,"timeSinceLastFire":-1,"enemies":71,"incomingShells":16,"spawnToDeathS":4.9,"dodgeDurationS":72.3,"shellAgeS":-1,"playerMovingTowardShell":false,"dodgeTowardShell":false}},{"type":"spawn","t":82855,"data":{"pos":[735,735]}},{"type":"kill","t":84502,"data":{"killNum":8,"wave":0}},{"type":"death","t":87175,"data":{"deathNum":9,"wave":0,"kills":8,"pos":[720,640],"cause":"self_shell","killer":{"ownerId":"p-e58594d6-f","isOwnShell":true,"dist":65,"shellSpeed":320,"shellPos":[735,703],"shellType":320,"shellAgeS":-1,"playerMovingTowardShell":false,"dodgeTowardShell":false},"playerSpeed":0,"playerVel":[0,0],"dodgeActive":true,"dodgeUrgency":0.4470567060305518,"dodgeMoveX":-0.21,"dodgeMoveZ":-0.98,"interceptActive":false,"timeSinceLastFire":-1,"enemies":71,"incomingShells":26,"spawnToDeathS":4.3,"dodgeDurationS":78.8,"shellAgeS":-1,"playerMovingTowardShell":false,"dodgeTowardShell":false}},{"type":"spawn","t":89400,"data":{"pos":[735,735]}},{"type":"kill","t":91000,"data":{"killNum":9,"wave":0}}],"summary":{"avgDodgeActive":0.912,"pathGuardTriggeredPct":0.794,"avgPredictedShells":50.42,"avgRealShells":9.03,"dodgeDirectionChanges":22,"killsOverTime":[[7200,1],[13900,2],[34000,3],[40100,4],[47600,5],[71000,6],[77400,7],[84502,8],[91000,9]],"deathsOverTime":[[3392,1],[10056,2],[30171,3],[36240,4],[43769,5],[67182,6],[73597,7],[80642,8],[87175,9]],"maxEnemies":72,"avgFps":60,"finalHp":1,"finalAlive":true,"wave":0}}