{"trialId":"v27-CA-025","version":"v27","map":"CA","levelId":"custom-c2738ec4-135","aimbotOff":false,"trialNum":25,"trialDurationMs":82599,"finalKills":4,"finalDeaths":1,"shotsFired":28,"frameData":[{"t":0,"playerX":1295,"playerZ":175,"hp":1,"dodgeActive":false,"dodgeMoveX":0,"dodgeMoveZ":0,"dodgeUrgency":0,"pathGuardEngaged":false,"pathGuardCrossCount":0,"predictedShellCount":0,"realShellCount":0,"aimHitProb":null,"aimBounces":0,"aimTargetId":null,"shellsInFlight":0,"shotsFiredCumulative":0},{"t":1100,"playerX":1295,"playerZ":175,"hp":1,"dodgeActive":false,"dodgeMoveX":0,"dodgeMoveZ":0,"dodgeUrgency":0,"pathGuardEngaged":false,"pathGuardCrossCount":0,"predictedShellCount":0,"realShellCount":0,"aimHitProb":null,"aimBounces":0,"aimTargetId":null,"shellsInFlight":0,"shotsFiredCumulative":0},{"t":2199,"playerX":1295,"playerZ":175,"hp":1,"dodgeActive":false,"dodgeMoveX":0,"dodgeMoveZ":0,"dodgeUrgency":0,"pathGuardEngaged":false,"pathGuardCrossCount":0,"predictedShellCount":0,"realShellCount":0,"aimHitProb":null,"aimBounces":0,"aimTargetId":null,"shellsInFlight":0,"shotsFiredCumulative":0},{"t":3299,"playerX":1295,"playerZ":175,"hp":1,"dodgeActive":false,"dodgeMoveX":0,"dodgeMoveZ":0,"dodgeUrgency":0,"pathGuardEngaged":false,"pathGuardCrossCount":0,"predictedShellCount":0,"realShellCount":0,"aimHitProb":1.1071487177940895,"aimBounces":0,"aimTargetId":null,"shellsInFlight":0,"shotsFiredCumulative":0},{"t":4399,"playerX":1295,"playerZ":175,"hp":1,"dodgeActive":false,"dodgeMoveX":0,"dodgeMoveZ":0,"dodgeUrgency":0,"pathGuardEngaged":false,"pathGuardCrossCount":0,"predictedShellCount":0,"realShellCount":0,"aimHitProb":1.1253899088097317,"aimBounces":0,"aimTargetId":null,"shellsInFlight":5,"shotsFiredCumulative":5},{"t":5402,"playerX":1295,"playerZ":175,"hp":1,"dodgeActive":false,"dodgeMoveX":0,"dodgeMoveZ":0,"dodgeUrgency":0,"pathGuardEngaged":false,"pathGuardCrossCount":0,"predictedShellCount":0,"realShellCount":0,"aimHitProb":1.134784842517023,"aimBounces":0,"aimTargetId":null,"shellsInFlight":5,"shotsFiredCumulative":5},{"t":6500,"playerX":1295,"playerZ":175,"hp":1,"dodgeActive":false,"dodgeMoveX":0,"dodgeMoveZ":0,"dodgeUrgency":0,"pathGuardEngaged":false,"pathGuardCrossCount":0,"predictedShellCount":0,"realShellCount":0,"aimHitProb":1.146812213186852,"aimBounces":0,"aimTargetId":null,"shellsInFlight":5,"shotsFiredCumulative":5},{"t":7501,"playerX":1295,"playerZ":175,"hp":1,"dodgeActive":false,"dodgeMoveX":0,"dodgeMoveZ":0,"dodgeUrgency":0,"pathGuardEngaged":false,"pathGuardCrossCount":0,"predictedShellCount":0,"realShellCount":0,"aimHitProb":0.04356988275902829,"aimBounces":0,"aimTargetId":null,"shellsInFlight":5,"shotsFiredCumulative":5},{"t":8599,"playerX":1295,"playerZ":175,"hp":1,"dodgeActive":false,"dodgeMoveX":0,"dodgeMoveZ":0,"dodgeUrgency":0,"pathGuardEngaged":false,"pathGuardCrossCount":0,"predictedShellCount":0,"realShellCount":0,"aimHitProb":0.2733405195655605,"aimBounces":0,"aimTargetId":null,"shellsInFlight":5,"shotsFiredCumulative":5},{"t":35299,"playerX":1295,"playerZ":175,"hp":1,"dodgeActive":false,"dodgeMoveX":0,"dodgeMoveZ":0,"dodgeUrgency":0,"pathGuardEngaged":false,"pathGuardCrossCount":0,"predictedShellCount":0,"realShellCount":0,"aimHitProb":null,"aimBounces":0,"aimTargetId":null,"shellsInFlight":5,"shotsFiredCumulative":5},{"t":36399,"playerX":1295,"playerZ":175,"hp":1,"dodgeActive":false,"dodgeMoveX":0,"dodgeMoveZ":0,"dodgeUrgency":0,"pathGuardEngaged":false,"pathGuardCrossCount":0,"predictedShellCount":0,"realShellCount":0,"aimHitProb":null,"aimBounces":0,"aimTargetId":null,"shellsInFlight":5,"shotsFiredCumulative":5},{"t":37499,"playerX":1295,"playerZ":175,"hp":1,"dodgeActive":false,"dodgeMoveX":0,"dodgeMoveZ":0,"dodgeUrgency":0,"pathGuardEngaged":false,"pathGuardCrossCount":0,"predictedShellCount":0,"realShellCount":0,"aimHitProb":null,"aimBounces":0,"aimTargetId":null,"shellsInFlight":5,"shotsFiredCumulative":5},{"t":38599,"playerX":1295,"playerZ":175,"hp":1,"dodgeActive":false,"dodgeMoveX":0,"dodgeMoveZ":0,"dodgeUrgency":0,"pathGuardEngaged":false,"pathGuardCrossCount":0,"predictedShellCount":0,"realShellCount":0,"aimHitProb":0.3362426903331013,"aimBounces":0,"aimTargetId":null,"shellsInFlight":2,"shotsFiredCumulative":6},{"t":39699,"playerX":1295,"playerZ":175,"hp":1,"dodgeActive":false,"dodgeMoveX":0,"dodgeMoveZ":0,"dodgeUrgency":0,"pathGuardEngaged":false,"pathGuardCrossCount":0,"predictedShellCount":0,"realShellCount":0,"aimHitProb":0.2931875389416483,"aimBounces":0,"aimTargetId":null,"shellsInFlight":3,"shotsFiredCumulative":7},{"t":40799,"playerX":1293,"playerZ":175,"hp":1,"dodgeActive":false,"dodgeMoveX":0,"dodgeMoveZ":0,"dodgeUrgency":0,"pathGuardEngaged":false,"pathGuardCrossCount":0,"predictedShellCount":0,"realShellCount":0,"aimHitProb":0.5020333287492047,"aimBounces":0,"aimTargetId":null,"shellsInFlight":4,"shotsFiredCumulative":8},{"t":41899,"playerX":1246,"playerZ":155,"hp":1,"dodgeActive":true,"dodgeMoveX":0.07,"dodgeMoveZ":1,"dodgeUrgency":0.5869925505857689,"pathGuardEngaged":false,"pathGuardCrossCount":0,"predictedShellCount":3,"realShellCount":6,"aimHitProb":0.588830201842903,"aimBounces":0,"aimTargetId":null,"shellsInFlight":4,"shotsFiredCumulative":8},{"t":42999,"playerX":1231,"playerZ":118,"hp":1,"dodgeActive":true,"dodgeMoveX":0.23,"dodgeMoveZ":0.97,"dodgeUrgency":0.5236008760105146,"pathGuardEngaged":false,"pathGuardCrossCount":0,"predictedShellCount":3,"realShellCount":6,"aimHitProb":0.8336734867778723,"aimBounces":0,"aimTargetId":null,"shellsInFlight":3,"shotsFiredCumulative":8},{"t":44099,"playerX":1231,"playerZ":118,"hp":1,"dodgeActive":true,"dodgeMoveX":0.23,"dodgeMoveZ":0.97,"dodgeUrgency":0.5236008760105146,"pathGuardEngaged":false,"pathGuardCrossCount":0,"predictedShellCount":3,"realShellCount":6,"aimHitProb":0.6649894287619063,"aimBounces":0,"aimTargetId":null,"shellsInFlight":4,"shotsFiredCumulative":9},{"t":45199,"playerX":1286,"playerZ":107,"hp":1,"dodgeActive":true,"dodgeMoveX":0.7,"dodgeMoveZ":-0.72,"dodgeUrgency":1,"pathGuardEngaged":false,"pathGuardCrossCount":0,"predictedShellCount":2,"realShellCount":6,"aimHitProb":0.6429584067644107,"aimBounces":0,"aimTargetId":null,"shellsInFlight":4,"shotsFiredCumulative":9},{"t":46299,"playerX":1188,"playerZ":121,"hp":1,"dodgeActive":true,"dodgeMoveX":-0.64,"dodgeMoveZ":0.77,"dodgeUrgency":1,"pathGuardEngaged":false,"pathGuardCrossCount":0,"predictedShellCount":2,"realShellCount":6,"aimHitProb":0.6524433739012103,"aimBounces":0,"aimTargetId":null,"shellsInFlight":5,"shotsFiredCumulative":10},{"t":47399,"playerX":1185,"playerZ":123,"hp":1,"dodgeActive":true,"dodgeMoveX":-0.64,"dodgeMoveZ":0.77,"dodgeUrgency":1,"pathGuardEngaged":false,"pathGuardCrossCount":0,"predictedShellCount":2,"realShellCount":6,"aimHitProb":0.501051254115847,"aimBounces":0,"aimTargetId":null,"shellsInFlight":2,"shotsFiredCumulative":10},{"t":48499,"playerX":1185,"playerZ":123,"hp":1,"dodgeActive":true,"dodgeMoveX":-0.64,"dodgeMoveZ":0.77,"dodgeUrgency":1,"pathGuardEngaged":false,"pathGuardCrossCount":0,"predictedShellCount":2,"realShellCount":6,"aimHitProb":0.824467328310277,"aimBounces":0,"aimTargetId":null,"shellsInFlight":2,"shotsFiredCumulative":10},{"t":49599,"playerX":1185,"playerZ":123,"hp":1,"dodgeActive":true,"dodgeMoveX":-0.64,"dodgeMoveZ":0.77,"dodgeUrgency":1,"pathGuardEngaged":false,"pathGuardCrossCount":0,"predictedShellCount":2,"realShellCount":6,"aimHitProb":0.4100923352517931,"aimBounces":0,"aimTargetId":null,"shellsInFlight":2,"shotsFiredCumulative":11},{"t":50699,"playerX":1185,"playerZ":123,"hp":1,"dodgeActive":true,"dodgeMoveX":-0.64,"dodgeMoveZ":0.77,"dodgeUrgency":1,"pathGuardEngaged":false,"pathGuardCrossCount":0,"predictedShellCount":2,"realShellCount":6,"aimHitProb":0.6504732014034396,"aimBounces":0,"aimTargetId":null,"shellsInFlight":3,"shotsFiredCumulative":12},{"t":51799,"playerX":1199,"playerZ":167,"hp":1,"dodgeActive":true,"dodgeMoveX":0.85,"dodgeMoveZ":-0.53,"dodgeUrgency":0.9147505885885705,"pathGuardEngaged":false,"pathGuardCrossCount":0,"predictedShellCount":2,"realShellCount":5,"aimHitProb":0.6142624693879721,"aimBounces":0,"aimTargetId":null,"shellsInFlight":5,"shotsFiredCumulative":14},{"t":52899,"playerX":1216,"playerZ":161,"hp":1,"dodgeActive":true,"dodgeMoveX":0.85,"dodgeMoveZ":-0.53,"dodgeUrgency":0.9147505885885705,"pathGuardEngaged":false,"pathGuardCrossCount":0,"predictedShellCount":2,"realShellCount":5,"aimHitProb":0.9754205669411888,"aimBounces":0,"aimTargetId":null,"shellsInFlight":4,"shotsFiredCumulative":14},{"t":53999,"playerX":1219,"playerZ":143,"hp":1,"dodgeActive":true,"dodgeMoveX":0.85,"dodgeMoveZ":-0.53,"dodgeUrgency":0.9147505885885705,"pathGuardEngaged":false,"pathGuardCrossCount":0,"predictedShellCount":2,"realShellCount":5,"aimHitProb":0.575837923627958,"aimBounces":0,"aimTargetId":null,"shellsInFlight":5,"shotsFiredCumulative":15},{"t":55099,"playerX":1219,"playerZ":143,"hp":1,"dodgeActive":true,"dodgeMoveX":0.85,"dodgeMoveZ":-0.53,"dodgeUrgency":0.9147505885885705,"pathGuardEngaged":false,"pathGuardCrossCount":0,"predictedShellCount":2,"realShellCount":5,"aimHitProb":0.9361160038285092,"aimBounces":0,"aimTargetId":null,"shellsInFlight":3,"shotsFiredCumulative":15},{"t":56199,"playerX":1219,"playerZ":144,"hp":1,"dodgeActive":true,"dodgeMoveX":0.85,"dodgeMoveZ":-0.53,"dodgeUrgency":0.9147505885885705,"pathGuardEngaged":false,"pathGuardCrossCount":0,"predictedShellCount":2,"realShellCount":5,"aimHitProb":0.0834450617584519,"aimBounces":0,"aimTargetId":null,"shellsInFlight":5,"shotsFiredCumulative":17},{"t":57299,"playerX":1219,"playerZ":144,"hp":1,"dodgeActive":true,"dodgeMoveX":0.85,"dodgeMoveZ":-0.53,"dodgeUrgency":0.9147505885885705,"pathGuardEngaged":false,"pathGuardCrossCount":0,"predictedShellCount":2,"realShellCount":5,"aimHitProb":0.39407258610882323,"aimBounces":0,"aimTargetId":null,"shellsInFlight":5,"shotsFiredCumulative":17},{"t":58399,"playerX":1219,"playerZ":144,"hp":1,"dodgeActive":true,"dodgeMoveX":0.85,"dodgeMoveZ":-0.53,"dodgeUrgency":0.9147505885885705,"pathGuardEngaged":false,"pathGuardCrossCount":0,"predictedShellCount":2,"realShellCount":5,"aimHitProb":0.1435141608785564,"aimBounces":0,"aimTargetId":null,"shellsInFlight":2,"shotsFiredCumulative":17},{"t":59499,"playerX":1219,"playerZ":144,"hp":1,"dodgeActive":true,"dodgeMoveX":0.85,"dodgeMoveZ":-0.53,"dodgeUrgency":0.9147505885885705,"pathGuardEngaged":false,"pathGuardCrossCount":0,"predictedShellCount":2,"realShellCount":5,"aimHitProb":0.014815084693257319,"aimBounces":0,"aimTargetId":null,"shellsInFlight":2,"shotsFiredCumulative":18},{"t":60599,"playerX":1219,"playerZ":144,"hp":1,"dodgeActive":true,"dodgeMoveX":0.85,"dodgeMoveZ":-0.53,"dodgeUrgency":0.9147505885885705,"pathGuardEngaged":false,"pathGuardCrossCount":0,"predictedShellCount":2,"realShellCount":5,"aimHitProb":0.013500657857024478,"aimBounces":0,"aimTargetId":null,"shellsInFlight":1,"shotsFiredCumulative":18},{"t":61699,"playerX":1219,"playerZ":144,"hp":1,"dodgeActive":true,"dodgeMoveX":0.85,"dodgeMoveZ":-0.53,"dodgeUrgency":0.9147505885885705,"pathGuardEngaged":false,"pathGuardCrossCount":0,"predictedShellCount":2,"realShellCount":5,"aimHitProb":1.166569057744514,"aimBounces":0,"aimTargetId":null,"shellsInFlight":2,"shotsFiredCumulative":19},{"t":62799,"playerX":1199,"playerZ":120,"hp":1,"dodgeActive":true,"dodgeMoveX":0.85,"dodgeMoveZ":-0.53,"dodgeUrgency":0.9147505885885705,"pathGuardEngaged":false,"pathGuardCrossCount":0,"predictedShellCount":2,"realShellCount":5,"aimHitProb":0.012683980259605931,"aimBounces":0,"aimTargetId":null,"shellsInFlight":3,"shotsFiredCumulative":20},{"t":63899,"playerX":1165,"playerZ":128,"hp":1,"dodgeActive":true,"dodgeMoveX":-0.66,"dodgeMoveZ":-0.75,"dodgeUrgency":1,"pathGuardEngaged":false,"pathGuardCrossCount":0,"predictedShellCount":1,"realShellCount":5,"aimHitProb":null,"aimBounces":0,"aimTargetId":null,"shellsInFlight":3,"shotsFiredCumulative":21},{"t":64999,"playerX":1165,"playerZ":128,"hp":1,"dodgeActive":true,"dodgeMoveX":-0.66,"dodgeMoveZ":-0.75,"dodgeUrgency":1,"pathGuardEngaged":false,"pathGuardCrossCount":0,"predictedShellCount":1,"realShellCount":5,"aimHitProb":null,"aimBounces":0,"aimTargetId":null,"shellsInFlight":2,"shotsFiredCumulative":21},{"t":66099,"playerX":1165,"playerZ":128,"hp":1,"dodgeActive":true,"dodgeMoveX":-0.66,"dodgeMoveZ":-0.75,"dodgeUrgency":1,"pathGuardEngaged":false,"pathGuardCrossCount":0,"predictedShellCount":1,"realShellCount":5,"aimHitProb":null,"aimBounces":0,"aimTargetId":null,"shellsInFlight":2,"shotsFiredCumulative":21},{"t":67199,"playerX":1165,"playerZ":128,"hp":1,"dodgeActive":true,"dodgeMoveX":-0.66,"dodgeMoveZ":-0.75,"dodgeUrgency":1,"pathGuardEngaged":false,"pathGuardCrossCount":0,"predictedShellCount":1,"realShellCount":5,"aimHitProb":null,"aimBounces":0,"aimTargetId":null,"shellsInFlight":2,"shotsFiredCumulative":21},{"t":68299,"playerX":1165,"playerZ":128,"hp":1,"dodgeActive":true,"dodgeMoveX":-0.66,"dodgeMoveZ":-0.75,"dodgeUrgency":1,"pathGuardEngaged":false,"pathGuardCrossCount":0,"predictedShellCount":1,"realShellCount":5,"aimHitProb":0.22510980235563416,"aimBounces":0,"aimTargetId":null,"shellsInFlight":3,"shotsFiredCumulative":22},{"t":69399,"playerX":1165,"playerZ":128,"hp":1,"dodgeActive":true,"dodgeMoveX":-0.66,"dodgeMoveZ":-0.75,"dodgeUrgency":1,"pathGuardEngaged":false,"pathGuardCrossCount":0,"predictedShellCount":1,"realShellCount":5,"aimHitProb":0.1671313045834495,"aimBounces":0,"aimTargetId":null,"shellsInFlight":2,"shotsFiredCumulative":22},{"t":70499,"playerX":1127,"playerZ":123,"hp":1,"dodgeActive":true,"dodgeMoveX":-0.66,"dodgeMoveZ":-0.75,"dodgeUrgency":1,"pathGuardEngaged":false,"pathGuardCrossCount":0,"predictedShellCount":1,"realShellCount":5,"aimHitProb":0.10848632116194779,"aimBounces":0,"aimTargetId":null,"shellsInFlight":1,"shotsFiredCumulative":22},{"t":71599,"playerX":1117,"playerZ":95,"hp":1,"dodgeActive":true,"dodgeMoveX":-0.9,"dodgeMoveZ":-0.44,"dodgeUrgency":1,"pathGuardEngaged":false,"pathGuardCrossCount":0,"predictedShellCount":3,"realShellCount":2,"aimHitProb":0.2151444107816296,"aimBounces":0,"aimTargetId":null,"shellsInFlight":0,"shotsFiredCumulative":22},{"t":72699,"playerX":1117,"playerZ":102,"hp":1,"dodgeActive":true,"dodgeMoveX":-0.91,"dodgeMoveZ":-0.41,"dodgeUrgency":1,"pathGuardEngaged":false,"pathGuardCrossCount":0,"predictedShellCount":3,"realShellCount":3,"aimHitProb":0.0945978864789705,"aimBounces":0,"aimTargetId":null,"shellsInFlight":2,"shotsFiredCumulative":24},{"t":73799,"playerX":1117,"playerZ":102,"hp":1,"dodgeActive":true,"dodgeMoveX":-0.91,"dodgeMoveZ":-0.41,"dodgeUrgency":1,"pathGuardEngaged":false,"pathGuardCrossCount":0,"predictedShellCount":3,"realShellCount":3,"aimHitProb":0.0805833482501992,"aimBounces":0,"aimTargetId":null,"shellsInFlight":2,"shotsFiredCumulative":24},{"t":74899,"playerX":1117,"playerZ":102,"hp":1,"dodgeActive":true,"dodgeMoveX":-0.91,"dodgeMoveZ":-0.41,"dodgeUrgency":1,"pathGuardEngaged":false,"pathGuardCrossCount":0,"predictedShellCount":3,"realShellCount":3,"aimHitProb":0.060598432568603755,"aimBounces":0,"aimTargetId":null,"shellsInFlight":2,"shotsFiredCumulative":24},{"t":75999,"playerX":1117,"playerZ":102,"hp":1,"dodgeActive":true,"dodgeMoveX":-0.91,"dodgeMoveZ":-0.41,"dodgeUrgency":1,"pathGuardEngaged":false,"pathGuardCrossCount":0,"predictedShellCount":3,"realShellCount":3,"aimHitProb":0.008386155428905084,"aimBounces":0,"aimTargetId":null,"shellsInFlight":2,"shotsFiredCumulative":24},{"t":77099,"playerX":1117,"playerZ":102,"hp":1,"dodgeActive":true,"dodgeMoveX":-0.91,"dodgeMoveZ":-0.41,"dodgeUrgency":1,"pathGuardEngaged":false,"pathGuardCrossCount":0,"predictedShellCount":3,"realShellCount":3,"aimHitProb":3.058473108845522,"aimBounces":0,"aimTargetId":null,"shellsInFlight":3,"shotsFiredCumulative":25},{"t":78199,"playerX":1087,"playerZ":104,"hp":1,"dodgeActive":true,"dodgeMoveX":-0.91,"dodgeMoveZ":-0.41,"dodgeUrgency":1,"pathGuardEngaged":false,"pathGuardCrossCount":0,"predictedShellCount":3,"realShellCount":3,"aimHitProb":0.19223555408518678,"aimBounces":0,"aimTargetId":null,"shellsInFlight":4,"shotsFiredCumulative":26},{"t":79299,"playerX":984,"playerZ":109,"hp":1,"dodgeActive":true,"dodgeMoveX":0.99,"dodgeMoveZ":0.1,"dodgeUrgency":1,"pathGuardEngaged":false,"pathGuardCrossCount":0,"predictedShellCount":1,"realShellCount":5,"aimHitProb":0.2498879231361375,"aimBounces":0,"aimTargetId":null,"shellsInFlight":5,"shotsFiredCumulative":27},{"t":80399,"playerX":888,"playerZ":120,"hp":1,"dodgeActive":true,"dodgeMoveX":0.97,"dodgeMoveZ":-0.26,"dodgeUrgency":1,"pathGuardEngaged":false,"pathGuardCrossCount":0,"predictedShellCount":2,"realShellCount":6,"aimHitProb":0.17770947517320046,"aimBounces":0,"aimTargetId":null,"shellsInFlight":3,"shotsFiredCumulative":27},{"t":81499,"playerX":854,"playerZ":100,"hp":1,"dodgeActive":true,"dodgeMoveX":0.97,"dodgeMoveZ":-0.26,"dodgeUrgency":1,"pathGuardEngaged":false,"pathGuardCrossCount":0,"predictedShellCount":2,"realShellCount":6,"aimHitProb":0.2602464555860635,"aimBounces":0,"aimTargetId":null,"shellsInFlight":4,"shotsFiredCumulative":28},{"t":82599,"playerX":854,"playerZ":100,"hp":1,"dodgeActive":true,"dodgeMoveX":0.97,"dodgeMoveZ":-0.26,"dodgeUrgency":1,"pathGuardEngaged":false,"pathGuardCrossCount":0,"predictedShellCount":2,"realShellCount":6,"aimHitProb":0.007356447804898636,"aimBounces":0,"aimTargetId":null,"shellsInFlight":4,"shotsFiredCumulative":28}],"events":[{"type":"boot","t":0,"data":{"mode":"passive"}},{"type":"wave","t":0,"data":{"from":0,"to":1}},{"type":"kill","t":6500,"data":{"killNum":1,"wave":1}},{"type":"death","t":9250,"data":{"deathNum":1,"wave":1,"kills":1,"pos":[1295,175],"cause":"unknown","killer":null,"playerSpeed":0,"playerVel":[0,0],"dodgeActive":false,"dodgeUrgency":0,"dodgeMoveX":0,"dodgeMoveZ":0,"interceptActive":false,"timeSinceLastFire":-1,"enemies":2,"incomingShells":0,"spawnToDeathS":9.3,"dodgeDurationS":0,"shellAgeS":-1,"playerMovingTowardShell":false,"dodgeTowardShell":false}},{"type":"spawn","t":35299,"data":{"pos":[1295,175]}},{"type":"kill","t":57699,"data":{"killNum":2,"wave":1}},{"type":"kill","t":63699,"data":{"killNum":3,"wave":2}},{"type":"wave","t":63699,"data":{"from":1,"to":2}},{"type":"kill","t":70699,"data":{"killNum":4,"wave":2}},{"type":"death","t":83048,"data":{"deathNum":2,"wave":2,"kills":4,"pos":[855,100],"cause":"unknown","killer":null,"playerSpeed":0,"playerVel":[0,0],"dodgeActive":true,"dodgeUrgency":1,"dodgeMoveX":0.97,"dodgeMoveZ":-0.26,"interceptActive":false,"timeSinceLastFire":-1,"enemies":2,"incomingShells":1,"spawnToDeathS":47.7,"dodgeDurationS":41.7,"shellAgeS":-1,"playerMovingTowardShell":false,"dodgeTowardShell":false}}],"summary":{"avgDodgeActive":0.717,"pathGuardTriggeredPct":0.0,"avgPredictedShells":2.05,"avgRealShells":4.92,"dodgeDirectionChanges":6,"killsOverTime":[[6500,1],[57699,2],[63699,3],[70699,4]],"deathsOverTime":[[9250,1],[83048,2]],"maxEnemies":4,"avgFps":60.3,"finalHp":1,"finalAlive":true,"wave":2}}